sdypy/EMA/EMA.py
sdypy/EMA/__init__.py
sdypy/EMA/normal_modes.py
sdypy/EMA/paper.bib
sdypy/EMA/pole_picking.py
sdypy/EMA/stabilization.py
sdypy/EMA/tools.py
sdypy_ema-0.29.1.dist-info/METADATA
sdypy_ema-0.29.1.dist-info/WHEEL
sdypy_ema-0.29.1.dist-info/licenses/LICENSE
sdypy_ema-0.29.1.dist-info/RECORD
