Metadata-Version: 2.4
Name: sdypy-EMA
Version: 0.29.1
Summary: Experimental and operational modal analysis.
Project-URL: homepage, https://github.com/sdypy/sdypy-EMA
Project-URL: documentation, https://sdypy-EMA.readthedocs.io/en/latest/index.html
Project-URL: source, https://github.com/sdypy/sdypy-EMA
Author-email: "Janko Slavič et al." <janko.slavic@fs.uni-lj.si>
Maintainer-email: "Janko Slavič et al." <janko.slavic@fs.uni-lj.si>
License-Expression: MIT
License-File: LICENSE
Keywords: EMA,Experimental Modal Analysis,OMA,Structural Dynamics
Classifier: Development Status :: 5 - Production/Stable
Classifier: Intended Audience :: Developers
Classifier: License :: OSI Approved :: MIT License
Classifier: Programming Language :: Python :: 3.10
Classifier: Topic :: Scientific/Engineering
Requires-Python: >=3.10
Requires-Dist: matplotlib>=3.3.1
Requires-Dist: numpy>=1.14.3
Requires-Dist: pyuff>=2.1
Requires-Dist: scipy>=1.1.0
Requires-Dist: tqdm>=4.23.4
Provides-Extra: dev
Requires-Dist: build; extra == 'dev'
Requires-Dist: pylump; extra == 'dev'
Requires-Dist: pytest; extra == 'dev'
Requires-Dist: sphinx; extra == 'dev'
Requires-Dist: sphinx-copybutton>=0.5.2; extra == 'dev'
Requires-Dist: sphinx-rtd-theme; extra == 'dev'
Requires-Dist: twine; extra == 'dev'
Requires-Dist: wheel; extra == 'dev'
